setup.py
paper/modopt_ex_16starship_benchmark.py
paper/simple_example.py
pyslsqp-0.1.4.dist-info/RECORD
pyslsqp-0.1.4.dist-info/WHEEL
pyslsqp-0.1.4.dist-info/top_level.txt
pyslsqp-0.1.4.dist-info/LICENSE.txt
pyslsqp-0.1.4.dist-info/METADATA
tests/testing_utils.py
tests/test_optimize.py
tests/test_docstring_examples.py
tests/test_docs.py
tests/test_save_and_load.py
pyslsqp/__init__.py
pyslsqp/visualize.py
pyslsqp/_slsqp.cpython-38-darwin.so
pyslsqp/save_and_load.py
pyslsqp/postprocessing.py
pyslsqp/main.py
pyslsqp/.dylibs/libgfortran.5.dylib
pyslsqp/.dylibs/libquadmath.0.dylib
pyslsqp/.dylibs/libgcc_s.1.1.dylib
docs/conf.py
