Metadata-Version: 2.2
Name: pyslsqp
Version: 0.1.4
Summary: A transparent Python interface to the SLSQP optimization algorithm, with advanced features and visualization capabilities.
Author-email: Anugrah Jo Joshy <ajoshy.ucsd@gmail.com>
Maintainer-email: Anugrah Jo Joshy <ajoshy.ucsd@gmail.com>
License: Copyright (c) 2024, Anugrah Jo Joshy.
Project-URL: Homepage/Repository, https://github.com/anugrahjo/pyslsqp
Project-URL: Documentation, https://pyslsqp.readthedocs.io/en/latest/
Project-URL: Bug Tracker, https://github.com/anugrahjo/pyslsqp/issues
Project-URL: Changelog, https://pyslsqp.readthedocs.io/en/latest/src/changelog.html
Project-URL: Download, https://pypi.org/project/pyslsqp/#files
Keywords: slsqp,optimization,optimization algorithm,nlp,optimizer,nonlinear programming,numerical optimization
Classifier: Development Status :: 5 - Production/Stable
Classifier: License :: OSI Approved :: BSD License
Classifier: Operating System :: MacOS
Classifier: Operating System :: POSIX :: Linux
Classifier: Programming Language :: Python
Classifier: Programming Language :: Python :: 3.8
Classifier: Programming Language :: Python :: 3.9
Classifier: Programming Language :: Python :: 3.10
Classifier: Programming Language :: Python :: 3.11
Classifier: Programming Language :: Python :: 3.12
Classifier: Intended Audience :: Developers
Classifier: Intended Audience :: Science/Research
Classifier: Natural Language :: English
Classifier: Topic :: Scientific/Engineering
Classifier: Topic :: Scientific/Engineering :: Mathematics
Classifier: Topic :: Software Development :: Libraries
Requires-Python: >=3.8
License-File: LICENSE.txt
Requires-Dist: numpy<3,>=1.24
Requires-Dist: h5py<4,>=3.11.0
Requires-Dist: matplotlib<4,>=3.4
